README.md
publish-to-DEV
publish-to-medium
setup.py
publish_markdown/__init__.py
publish_markdown/publishers.py
publish_markdown.egg-info/PKG-INFO
publish_markdown.egg-info/SOURCES.txt
publish_markdown.egg-info/dependency_links.txt
publish_markdown.egg-info/requires.txt
publish_markdown.egg-info/top_level.txt