Metadata-Version: 2.1
Name: publish-markdown
Version: 0.2.1
Summary: Publish articles written in Markdown files to medium.com, dev.to, hashnode and twitter
Home-page: https://github.com/nottrobin/publish-markdown
Author: Robin Winslow
Author-email: robin@robinwinslow.co.uk
License: UNKNOWN
Platform: UNKNOWN
